LICENSE
README.md
doc/zs-yaml.png
doc/zs-yaml.svg
zs_yaml/__init__.py
zs_yaml/_version.py
zs_yaml/built_in_transformations.py
zs_yaml/convert.py
zs_yaml/main.py
zs_yaml/yaml_transformer.py
zs_yaml-0.8.3.dist-info/licenses/LICENSE
zs_yaml-0.8.3.dist-info/METADATA
zs_yaml-0.8.3.dist-info/WHEEL
zs_yaml-0.8.3.dist-info/entry_points.txt
zs_yaml-0.8.3.dist-info/top_level.txt
zs_yaml-0.8.3.dist-info/RECORD
