Metadata-Version: 2.4
Name: zs-yaml
Version: 0.8.3
Summary: YAML support for zserio
Author-email: "Navigation Data Standard e.V." <support@nds-association.org>
License-Expression: MIT
Project-URL: Homepage, https://github.com/ndsev/zs-yaml
Project-URL: Repository, https://github.com/ndsev/zs-yaml
Project-URL: Issues, https://github.com/ndsev/zs-yaml/issues
Classifier: Development Status :: 4 - Beta
Classifier: Intended Audience :: Developers
Classifier: Operating System :: OS Independent
Classifier: Programming Language :: Python :: 3
Classifier: Programming Language :: Python :: 3.8
Classifier: Programming Language :: Python :: 3.9
Classifier: Programming Language :: Python :: 3.10
Classifier: Programming Language :: Python :: 3.11
Classifier: Programming Language :: Python :: 3.12
Classifier: Topic :: Software Development :: Build Tools
Classifier: Topic :: Software Development :: Code Generators
Requires-Python: >=3.8
License-File: LICENSE
Requires-Dist: PyYAML~=6.0
Requires-Dist: zserio<3,>=2.15.0
Requires-Dist: zstandard
Requires-Dist: lz4
Requires-Dist: brotli
Dynamic: license-file
